{"query":{"recentchanges":[{"type":"edit","ns":0,"title":"\u5927\u7389\u6751\u7acb\u7389\u4e95\u5c0f\u5b66\u6821","user":"MasaoBot","timestamp":"2011-12-27T11:00:00Z"},{"type":"edit","ns":0,"title":"\u5927\u7389\u6751\u7acb\u5927\u7389\u4e2d\u5b66\u6821","user":"MasaoBot","timestamp":"2011-12-27T11:00:21Z"},{"type":"edit","ns":0,"title":"\u5927\u7389\u6751\u7acb\u5927\u5c71\u5c0f\u5b66\u6821","user":"MasaoBot","timestamp":"2011-12-27T11:00:41Z"},{"type":"edit","ns":0,"title":"\u5927\u718a\u753a\u7acb\u718a\u753a\u5c0f\u5b66\u6821","user":"MasaoBot","timestamp":"2011-12-27T11:01:00Z"},{"type":"edit","ns":0,"title":"\u5927\u718a\u753a\u7acb\u5927\u718a\u4e2d\u5b66\u6821","user":"MasaoBot","timestamp":"2011-12-27T11:01:19Z"},{"type":"edit","ns":0,"title":"\u5927\u718a\u753a\u7acb\u5927\u91ce\u5c0f\u5b66\u6821","user":"MasaoBot","timestamp":"2011-12-27T11:01:39Z"},{"type":"edit","ns":0,"title":"\u5927\u6c5f\u753a\u7acb\u5de6\u6ca2\u5c0f\u5b66\u6821","user":"MasaoBot","timestamp":"2011-12-27T11:02:00Z"},{"type":"edit","ns":0,"title":"\u5927\u6c5f\u753a\u7acb\u4e09\u90f7\u5c0f\u5b66\u6821","user":"MasaoBot","timestamp":"2011-12-27T11:02:19Z"},{"type":"edit","ns":0,"title":"\u5927\u6c5f\u753a\u7acb\u4e03\u8ed2\u897f\u5c0f\u5b66\u6821","user":"MasaoBot","timestamp":"2011-12-27T11:02:40Z"},{"type":"edit","ns":0,"title":"\u5927\u6c5f\u753a\u7acb\u4e03\u8ed2\u6771\u5c0f\u5b66\u6821","user":"MasaoBot","timestamp":"2011-12-27T11:02:59Z"},{"type":"edit","ns":0,"title":"\u5927\u6c5f\u753a\u7acb\u5927\u6c5f\u4e2d\u5b66\u6821","user":"MasaoBot","timestamp":"2011-12-27T11:03:19Z"},{"type":"edit","ns":0,"title":"\u5927\u6c5f\u753a\u7acb\u672c\u90f7\u897f\u5c0f\u5b66\u6821","user":"MasaoBot","timestamp":"2011-12-27T11:03:40Z"},{"type":"edit","ns":0,"title":"\u5927\u6c5f\u753a\u7acb\u672c\u90f7\u6771\u5c0f\u5b66\u6821","user":"MasaoBot","timestamp":"2011-12-27T11:04:00Z"},{"type":"edit","ns":0,"title":"\u5927\u5b50\u753a\u7acb\u3055\u306f\u3089\u5c0f\u5b66\u6821","user":"MasaoBot","timestamp":"2011-12-27T11:04:19Z"},{"type":"edit","ns":0,"title":"\u5927\u5b50\u753a\u7acb\u3060\u3044\u3054\u5c0f\u5b66\u6821","user":"MasaoBot","timestamp":"2011-12-27T11:04:39Z"},{"type":"edit","ns":0,"title":"\u5927\u5b50\u753a\u7acb\u4f9d\u4e0a\u5c0f\u5b66\u6821","user":"MasaoBot","timestamp":"2011-12-27T11:04:58Z"},{"type":"edit","ns":0,"title":"\u5927\u5b50\u753a\u7acb\u9ed2\u6ca2\u5c0f\u5b66\u6821","user":"MasaoBot","timestamp":"2011-12-27T11:05:19Z"},{"type":"edit","ns":0,"title":"\u5927\u5b50\u753a\u7acb\u4e0a\u5c0f\u5ddd\u5c0f\u5b66\u6821","user":"MasaoBot","timestamp":"2011-12-27T11:05:28Z"},{"type":"edit","ns":0,"title":"\u5927\u6771\u5b66\u5712\u9ad8\u7b49\u5b66\u6821","user":"MasaoBot","timestamp":"2011-12-27T11:05:39Z"},{"type":"edit","ns":0,"title":"\u5927\u548c\u5e02\u7acb\u6e0b\u8c37\u4e2d\u5b66\u6821","user":"MasaoBot","timestamp":"2011-12-27T11:05:49Z"},{"type":"edit","ns":0,"title":"\u5927\u548c\u5e02\u7acb\u6587\u30f6\u5ca1\u5c0f\u5b66\u6821","user":"MasaoBot","timestamp":"2011-12-27T11:05:59Z"},{"type":"edit","ns":0,"title":"\u5927\u548c\u753a\u7acb\u5409\u5ca1\u5c0f\u5b66\u6821","user":"MasaoBot","timestamp":"2011-12-27T11:06:09Z"},{"type":"edit","ns":0,"title":"\u6edd\u6ca2\u6751\u7acb\u59e5\u5c4b\u6577\u5c0f\u5b66\u6821","user":"MasaoBot","timestamp":"2011-12-27T11:06:19Z"},{"type":"edit","ns":0,"title":"\u6edd\u6ca2\u6751\u7acb\u6edd\u6ca2\u5357\u4e2d\u5b66\u6821","user":"MasaoBot","timestamp":"2011-12-27T11:06:29Z"},{"type":"edit","ns":0,"title":"\u6edd\u6ca2\u6751\u7acb\u67f3\u6ca2\u5c0f\u5b66\u6821","user":"MasaoBot","timestamp":"2011-12-27T11:06:39Z"},{"type":"edit","ns":0,"title":"\u53ea\u898b\u753a\u7acb\u53ea\u898b\u4e2d\u5b66\u6821","user":"MasaoBot","timestamp":"2011-12-27T11:06:49Z"},{"type":"edit","ns":0,"title":"\u68da\u5009\u753a\u7acb\u8fd1\u6d25\u5c0f\u5b66\u6821","user":"MasaoBot","timestamp":"2011-12-27T11:06:59Z"},{"type":"edit","ns":0,"title":"\u68da\u5009\u753a\u7acb\u793e\u5ddd\u5c0f\u5b66\u6821","user":"MasaoBot","timestamp":"2011-12-27T11:07:09Z"},{"type":"edit","ns":0,"title":"\u7b51\u897f\u5e02\u7acb\u4f0a\u8b83\u5c0f\u5b66\u6821","user":"MasaoBot","timestamp":"2011-12-27T11:07:19Z"},{"type":"edit","ns":0,"title":"\u7b51\u897f\u5e02\u7acb\u95a2\u57ce\u897f\u5c0f\u5b66\u6821","user":"MasaoBot","timestamp":"2011-12-27T11:07:29Z"},{"type":"edit","ns":0,"title":"\u7b51\u897f\u5e02\u7acb\u5927\u7530\u5c0f\u5b66\u6821","user":"MasaoBot","timestamp":"2011-12-27T11:07:39Z"},{"type":"edit","ns":0,"title":"\u7b51\u897f\u5e02\u7acb\u9577\u8b83\u5c0f\u5b66\u6821","user":"MasaoBot","timestamp":"2011-12-27T11:07:49Z"},{"type":"edit","ns":0,"title":"\u7b51\u897f\u5e02\u7acb\u9ce5\u7fbd\u5c0f\u5b66\u6821","user":"MasaoBot","timestamp":"2011-12-27T11:07:59Z"},{"type":"edit","ns":0,"title":"\u4e2d\u4e4b\u6761\u753a\u7acb\u540d\u4e45\u7530\u5c0f\u5b66\u6821","user":"MasaoBot","timestamp":"2011-12-27T11:08:09Z"},{"type":"edit","ns":0,"title":"\u4e2d\u4e4b\u6761\u753a\u7acb\u516d\u5408\u5c0f\u5b66\u6821","user":"MasaoBot","timestamp":"2011-12-27T11:08:19Z"},{"type":"edit","ns":0,"title":"\u4e2d\u4e4b\u6761\u753a\u7acb\u516d\u5408\u4e2d\u5b66\u6821","user":"MasaoBot","timestamp":"2011-12-27T11:08:29Z"},{"type":"edit","ns":0,"title":"\u732a\u82d7\u4ee3\u753a\u7acb\u6771\u4e2d\u5b66\u6821","user":"MasaoBot","timestamp":"2011-12-27T11:08:38Z"},{"type":"edit","ns":0,"title":"\u9577\u4e95\u5e02\u7acb\u4f0a\u4f50\u6ca2\u5c0f\u5b66\u6821","user":"MasaoBot","timestamp":"2011-12-27T11:08:49Z"}]}}